pyloggerutils/__init__.py
pyloggerutils/logger.py
pyloggerutils-0.1.2.dist-info/LICENSE
pyloggerutils-0.1.2.dist-info/METADATA
pyloggerutils-0.1.2.dist-info/WHEEL
pyloggerutils-0.1.2.dist-info/top_level.txt
pyloggerutils-0.1.2.dist-info/RECORD
